rda_python_dsupdt/PgUpdt.py
rda_python_dsupdt/__init__.py
rda_python_dsupdt/ds_updt.py
rda_python_dsupdt/dsupdt.py
rda_python_dsupdt/dsupdt.usg
rda_python_dsupdt/pg_updt.py
rda_python_dsupdt-2.0.9.dist-info/licenses/LICENSE
rda_python_dsupdt-2.0.9.dist-info/METADATA
rda_python_dsupdt-2.0.9.dist-info/WHEEL
rda_python_dsupdt-2.0.9.dist-info/entry_points.txt
rda_python_dsupdt-2.0.9.dist-info/top_level.txt
rda_python_dsupdt-2.0.9.dist-info/RECORD
